bitdeer/__init__.py
bitdeer/ai/__init__.py
bitdeer/ai/training/__init__.py
bitdeer/ai/training/client.py
bitdeer/ai/training/model.py
bitdeer/ai/training/resource_pb2.py
bitdeer/ai/training/training_pb2.py
bitdeer/ai/training/training_pb2_grpc.py
Btdr_AI-0.0.2.dist-info/METADATA
Btdr_AI-0.0.2.dist-info/WHEEL
Btdr_AI-0.0.2.dist-info/top_level.txt
Btdr_AI-0.0.2.dist-info/RECORD
