Metadata-Version: 2.1
Name: Btdr-AI
Version: 0.0.2
Summary: A Python SDK for Btdr AI platform.
Author: Luka
Author-email: luka@bitdeer.com
Classifier: Programming Language :: Python :: 3
Classifier: License :: OSI Approved :: MIT License
Classifier: Operating System :: OS Independent
Requires-Python: >=3.6
Requires-Dist: grpcio ==1.64.1
Requires-Dist: protobuf ==5.27.2
Requires-Dist: pydantic ==2.8.1
